Metadata-Version: 2.1
Name: fala-assis
Version: 0.0.1
Summary: Assistente de fala que avisa um portador de deficiência visual quando o programa executou
Home-page: https://github.com/OseiasBeu/AssistenteDeFala
Author: Oseias Beu
Author-email: oseiasbeu@outlook.com
License: MIT License
Keywords: Assistente de Fala
Platform: UNKNOWN
